huscy/subjects/__init__.py
huscy/subjects/admin.py
huscy/subjects/apps.py
huscy/subjects/models.py
huscy/subjects/pagination.py
huscy/subjects/permissions.py
huscy/subjects/serializers.py
huscy/subjects/services.py
huscy/subjects/urls.py
huscy/subjects/views.py
huscy/subjects/migrations/0001_initial.py
huscy/subjects/migrations/0001_squashed_0009_delete_contactold.py
huscy/subjects/migrations/0002_auto_20210810_0124.py
huscy/subjects/migrations/0003_auto_20211028_1133.py
huscy/subjects/migrations/0004_delete_note.py
huscy/subjects/migrations/0005_auto_20221011_0432.py
huscy/subjects/migrations/0006_rename_contact_contactold.py
huscy/subjects/migrations/0007_contact.py
huscy/subjects/migrations/0008_auto_20221018_0935.py
huscy/subjects/migrations/0009_delete_contactold.py
huscy/subjects/migrations/0010_delete_patient.py
huscy/subjects/migrations/0011_delete_inactivity.py
huscy/subjects/migrations/0012_alter_subject_contact.py
huscy/subjects/migrations/0013_alter_subject_options_subject_is_child_delete_child.py
huscy/subjects/migrations/0014_rename_subject_guardians_to_legal_representatives.py
huscy/subjects/migrations/0015_alter_subject_options.py
huscy/subjects/migrations/__init__.py
huscy_subjects-3.0.1.dist-info/licenses/LICENSE
huscy_subjects-3.0.1.dist-info/METADATA
huscy_subjects-3.0.1.dist-info/WHEEL
huscy_subjects-3.0.1.dist-info/top_level.txt
huscy_subjects-3.0.1.dist-info/RECORD
