Metadata-Version: 2.4
Name: huscy.subjects
Version: 3.0.1
Summary: Managing subjects in a human research context.
Home-page: https://bitbucket.org/huscy/subjects
Author: Mathias Goldau, Stefan Bunde
Author-email: stefanbunde+git@posteo.de
License: AGPLv3+
Classifier: Development Status :: 5 - Production/Stable
Classifier: License :: OSI Approved :: GNU Affero General Public License v3 or later (AGPLv3+)
Classifier: Operating System :: OS Independent
Classifier: Programming Language :: Python
Classifier: Programming Language :: Python :: 3
Classifier: Programming Language :: Python :: 3 :: Only
Classifier: Programming Language :: Python :: 3.8
Classifier: Programming Language :: Python :: 3.9
Classifier: Programming Language :: Python :: 3.10
Classifier: Programming Language :: Python :: 3.11
Classifier: Programming Language :: Python :: 3.12
Classifier: Programming Language :: Python :: 3.13
Classifier: Framework :: Django
Classifier: Framework :: Django :: 4.2
Classifier: Framework :: Django :: 5.0
Classifier: Framework :: Django :: 5.1
License-File: LICENSE
Requires-Dist: Django>=4.2
Requires-Dist: djangorestframework>=3.14
Requires-Dist: django-countries>=7.1
Requires-Dist: django-guardian>=2.2
Requires-Dist: django-phonenumber-field[phonenumberslite]>=5.1
Requires-Dist: django-reversion>=4
Requires-Dist: drf-nested-routers>=0.90
Provides-Extra: development
Requires-Dist: psycopg2-binary; extra == "development"
Provides-Extra: testing
Requires-Dist: tox; extra == "testing"
Requires-Dist: watchdog; extra == "testing"
Dynamic: author
Dynamic: author-email
Dynamic: classifier
Dynamic: description
Dynamic: description-content-type
Dynamic: home-page
Dynamic: license
Dynamic: license-file
Dynamic: provides-extra
Dynamic: requires-dist
Dynamic: summary
